abba/__init__.py
abba/models/f41/f41.ftz
abba/modules/__init__.py
abba/modules/f41.py
abba/modules/model_path.py
abba_model_f41-0.0.9.dist-info/LICENSE
abba_model_f41-0.0.9.dist-info/METADATA
abba_model_f41-0.0.9.dist-info/WHEEL
abba_model_f41-0.0.9.dist-info/top_level.txt
abba_model_f41-0.0.9.dist-info/RECORD
