Metadata-Version: 2.1
Name: abba-model-f41
Version: 0.0.9
Summary: sample
Home-page: https://github.com/
Author: abba
Author-email: jaebin9274@cogniterm.com
License: MIT
Platform: UNKNOWN
Classifier: Programming Language :: Python :: 3
Classifier: License :: OSI Approved :: MIT License
Classifier: Operating System :: OS Independent
Requires-Dist: fasttext (==0.9.2)
Requires-Dist: langid (==1.1.6)
Requires-Dist: numpy (==1.24.1)
Requires-Dist: pandas (==1.5.3)
Requires-Dist: pybind11 (==2.10.3)
Requires-Dist: python-dateutil (==2.8.2)
Requires-Dist: pytz (==2022.7.1)
Requires-Dist: six (==1.16.0)
Requires-Dist: tqdm (==4.64.1)
